Workbook

Sheet Resumen
A1: RESUMEN EJECUTIVO — NEGOCIO DE PERFUMES
A2: =" Actualizado al " & TEXT(TODAY(),"DD/MM/YYYY") -> Actualizado al 17/03/2026
B4: 💰 TOTAL INVERTIDO | E4: 📈 INGRESOS VENTAS | H4: ✅ GANANCIA NETA | K4: 🎯 ROI
B5: =Ganancias!B4 -> 302900 | E5: =Ganancias!B5 -> 0 | H5: =Ganancias!B8 -> 0 | K5: =IFERROR(Ganancias!E8/100,0) -> 0
B7: Costo total de compras | E7: Ventas confirmadas ☑ | H7: Ingresos − Costo vendido | K7: Retorno s/ inversión
B10: UNIDADES EN STOCK | E10: UNIDADES VENDIDAS | H10: PRODUCTOS DISTINTOS | K10: RECIBOS DE COMPRA
B11: {=SUMPRODUCT((Ganancias!B11:B31)-(Ganancias!C11:C31))} -> 21 | E11: =Ganancias!C32 -> 0 | H11: =COUNTA(Precios!A4:A24) -> 21 | K11: =3 -> 3
B16: 🚦 Estado del Stock por Producto | H16: 🏆 Top 5 Productos por Inversión
B17: Producto | D17: Stock | E17: Comprado | F17: Vendido | H17: Producto | K17: Costo ($) | L17: % Total
B18: QAED AL FURSAN EDP 90ML HOMBRE | D18: =Ganancias!E11 -> 🟡 Stock bajo | E18: =Ganancias!B11 -> 1 | F18: =Ganancias!C11 -> 0 | H18: 1. VULCAN FEU EDP 100ML UNISEX | K18: =Gastos!E7 -> 21900 | L18: =IFERROR(K18/Ganancias!B4*100,0) -> 7.2301089
B19: ECLAIR EDP 35ML MUJER | D19: =Ganancias!E12 -> 🟡 Stock bajo | E19: =Ganancias!B12 -> 1 | F19: =Ganancias!C12 -> 0 | H19: 2. MAS EDP 100ML UNISEX | K19: =Gastos!E6 -> 13900 | L19: =IFERROR(K19/Ganancias!B4*100,0) -> 4.5889733
B20: RAVE NOW EDP 100ML UNISEX | D20: =Ganancias!E13 -> 🟡 Stock bajo | E20: =Ganancias!B13 -> 1 | F20: =Ganancias!C13 -> 0 | H20: 3. HAWAS ICE EDP 100ML HOMBRE | K20: =Gastos!E12 -> 11900 | L20: =IFERROR(K20/Ganancias!B4*100,0) -> 3.9286893
B21: HAWAS FOR HIM EDP 100ML HOMBRE | D21: =Ganancias!E14 -> 🟡 Stock bajo | E21: =Ganancias!B14 -> 1 | F21: =Ganancias!C14 -> 0 | H21: 4. AQUATICA EDP 100ML HOMBRE | K21: =Gastos!E5 -> 3900 | L21: =IFERROR(K21/Ganancias!B4*100,0) -> 1.2875536
B22: AQUATICA EDP 100ML HOMBRE | D22: =Ganancias!E15 -> 🟡 Stock bajo | E22: =Ganancias!B15 -> 1 | F22: =Ganancias!C15 -> 0 | H22: 5. MUESTRA 5ML UNISEX | K22: =Gastos!E21 -> 2900 | L22: =IFERROR(K22/Ganancias!B4*100,0) -> 0.95741169
B23: MAS EDP 100ML UNISEX | D23: =Ganancias!E16 -> 🟡 Stock bajo | E23: =Ganancias!B16 -> 1 | F23: =Ganancias!C16 -> 0
B24: VULCAN FEU EDP 100ML UNISEX | D24: =Ganancias!E17 -> 🟡 Stock bajo | E24: =Ganancias!B17 -> 1 | F24: =Ganancias!C17 -> 0
B25: ASAD ELIXIR EDP 100ML HOMBRE | D25: =Ganancias!E18 -> 🟡 Stock bajo | E25: =Ganancias!B18 -> 1 | F25: =Ganancias!C18 -> 0
B26: HAYAATI EDP 100ML HOMBRE | D26: =Ganancias!E19 -> 🟡 Stock bajo | E26: =Ganancias!B19 -> 1 | F26: =Ganancias!C19 -> 0
B27: MANDARIN SKY EDP 100ML HOMBRE | D27: =Ganancias!E20 -> 🟡 Stock bajo | E27: =Ganancias!B20 -> 1 | F27: =Ganancias!C20 -> 0
B28: LIQUID BRUN EDP 100ML UNISEX | D28: =Ganancias!E21 -> 🟡 Stock bajo | E28: =Ganancias!B21 -> 1 | F28: =Ganancias!C21 -> 0
B29: HAWAS ICE EDP 100ML HOMBRE | D29: =Ganancias!E22 -> 🟡 Stock bajo | E29: =Ganancias!B22 -> 1 | F29: =Ganancias!C22 -> 0
B30: ASAD EDP 30ML HOMBRE | D30: =Ganancias!E23 -> 🟡 Stock bajo | E30: =Ganancias!B23 -> 1 | F30: =Ganancias!C23 -> 0
B31: OUD FOR GLORY WHITE EDP 30ML UNISEX | D31: =Ganancias!E24 -> 🟡 Stock bajo | E31: =Ganancias!B24 -> 1 | F31: =Ganancias!C24 -> 0
B32: SCANDAL EDP 25ML HOMBRE | D32: =Ganancias!E25 -> 🟡 Stock bajo | E32: =Ganancias!B25 -> 1 | F32: =Ganancias!C25 -> 0
B33: SCANDAL WOMEN EDP 30ML MUJER | D33: =Ganancias!E26 -> 🟡 Stock bajo | E33: =Ganancias!B26 -> 1 | F33: =Ganancias!C26 -> 0
B34: SARA CANDY EDP 30ML MUJER | D34: =Ganancias!E27 -> 🟡 Stock bajo | E34: =Ganancias!B27 -> 1 | F34: =Ganancias!C27 -> 0
... B38: MUESTRA 5ML UNISEX | D38: =Ganancias!E31 -> 🟡 Stock bajo | E38: =Ganancias!B31 -> 1 | F38: =Ganancias!C31 -> 0
B39: TOTAL | E39: =SUM(E18:E38) -> 21 | F39: =SUM(F18:F38) -> 0
B40: 📊 Inversión por Producto | H40: 🥧 Inversión por Recibo
A63: Datos actualizados automaticamente. Registra ventas en hoja Ventas (☑) → los KPI y graficos se actualizan solos.

Sheet Precios
A1: LISTA DE PRECIOS - PERFUMES
A2: Costo cargado del recibo ✔ → Ahora ingresa el Margen % en col C para ver el Precio de Venta calculado automaticamente
A3: Producto | B3: Costo de Compra ($) | C3: Margen (%) | D3: Precio de Venta ($) | E3: Ganancia por Unidad ($)
A4: QAED AL FURSAN EDP 90ML HOMBRE | B4: 11900 | C4: 0.3 | D4: =IF(OR(B4="",C4=""),"⚠ Completar costo y margen",B4/(1-C4)) -> 17000 | E4: =IF(OR(B4="",C4=""),"",D4-B4) -> 5100
A5: ECLAIR EDP 35ML MUJER | B5: 3900 | C5: 0.6 | D5: =IF(OR(B5="",C5=""),"⚠ Completar costo y margen",B5/(1-C5)) -> 9750 | E5: =IF(OR(B5="",C5=""),"",D5-B5) -> 5850
A6: RAVE NOW EDP 100ML UNISEX | B6: 13900 | D6: =IF(OR(B6="",C6=""),"⚠ Completar costo y margen",B6/(1-C6)) -> ⚠ Completar costo y margen | E6: =IF(OR(B6="",C6=""),"",D6-B6)
A7: HAWAS FOR HIM EDP 100ML HOMBRE | B7: 21900 | D7: =IF(OR(B7="",C7=""),"⚠ Completar costo y margen",B7/(1-C7)) -> ⚠ Completar costo y margen | E7: =IF(OR(B7="",C7=""),"",D7-B7)
A8: AQUATICA EDP 100ML HOMBRE | B8: 25900 | D8: =IF(OR(B8="",C8=""),"⚠ Completar costo y margen",B8/(1-C8)) -> ⚠ Completar costo y margen | E8: =IF(OR(B8="",C8=""),"",D8-B8)
A9: MAS EDP 100ML UNISEX | B9: 29900 | D9: =IF(OR(B9="",C9=""),"⚠ Completar costo y margen",B9/(1-C9)) -> ⚠ Completar costo y margen | E9: =IF(OR(B9="",C9=""),"",D9-B9)
A10: VULCAN FEU EDP 100ML UNISEX | B10: 32900 | D10: =IF(OR(B10="",C10=""),"⚠ Completar costo y margen",B10/(1-C10)) -> ⚠ Completar costo y margen | E10: =IF(OR(B10="",C10=""),"",D10-B10)
A11: ASAD ELIXIR EDP 100ML HOMBRE | B11: 23900 | D11: =IF(OR(B11="",C11=""),"⚠ Completar costo y margen",B11/(1-C11)) -> ⚠ Completar costo y margen | E11: =IF(OR(B11="",C11=""),"",D11-B11)
A12: HAYAATI EDP 100ML HOMBRE | B12: 11900 | D12: =IF(OR(B12="",C12=""),"⚠ Completar costo y margen",B12/(1-C12)) -> ⚠ Completar costo y margen | E12: =IF(OR(B12="",C12=""),"",D12-B12)
A13: MANDARIN SKY EDP 100ML HOMBRE | B13: 25900 | D13: =IF(OR(B13="",C13=""),"⚠ Completar costo y margen",B13/(1-C13)) -> ⚠ Completar costo y margen | E13: =IF(OR(B13="",C13=""),"",D13-B13)
A14: LIQUID BRUN EDP 100ML UNISEX | B14: 24900 | D14: =IF(OR(B14="",C14=""),"⚠ Completar costo y margen",B14/(1-C14)) -> ⚠ Completar costo y margen | E14: =IF(OR(B14="",C14=""),"",D14-B14)
A15: HAWAS ICE EDP 100ML HOMBRE | B15: 26900 | D15: =IF(OR(B15="",C15=""),"⚠ Completar costo y margen",B15/(1-C15)) -> ⚠ Completar costo y margen | E15: =IF(OR(B15="",C15=""),"",D15-B15)
A16: ASAD EDP 30ML HOMBRE | B16: 2900 | D16: =IF(OR(B16="",C16=""),"⚠ Completar costo y margen",B16/(1-C16)) -> ⚠ Completar costo y margen | E16: =IF(OR(B16="",C16=""),"",D16-B16)
A17: OUD FOR GLORY WHITE EDP 30ML UNISEX | B17: 2900 | D17: =IF(OR(B17="",C17=""),"⚠ Completar costo y margen",B17/(1-C17)) -> ⚠ Completar costo y margen | E17: =IF(OR(B17="",C17=""),"",D17-B17)
... A24: MUESTRA 5ML UNISEX | B24: 22000 | D24: =IF(OR(B24="",C24=""),"⚠ Completar costo y margen",B24/(1-C24)) -> ⚠ Completar costo y margen | E24: =IF(OR(B24="",C24=""),"",D24-B24)
A26: Azul = ingresa vos el valor | Negro/negrita = calculado automaticamente
A27: Amarillo = completar costo y margen | Formula: Precio Venta = Costo / (1 - Margen%)

Sheet Gastos
A1: REGISTRO DE COMPRAS - PERFUMES
A2: Registra cada compra: fecha, producto, cantidad y monto → el total se calcula automaticamente
A3: Fecha | B3: Producto / Descripcion | C3: Cantidad (unidades) | D3: Precio Unit. ($) | E3: Total Gastado ($) | F3: Notas
A4: 45717 | B4: QAED AL FURSAN EDP 90ML HOMBRE | C4: 1 | D4: 11900 | E4: =C4*D4 -> 11900 | F4: Recibo #21395
A5: 45717 | B5: ECLAIR EDP 35ML MUJER | C5: 1 | D5: 3900 | E5: =C5*D5 -> 3900 | F5: Recibo #21395
A6: 45717 | B6: RAVE NOW EDP 100ML UNISEX | C6: 1 | D6: 13900 | E6: =C6*D6 -> 13900 | F6: Recibo #21395
A7: 45717 | B7: HAWAS FOR HIM EDP 100ML HOMBRE | C7: 1 | D7: 21900 | E7: =C7*D7 -> 21900 | F7: Recibo #21395
A8: 45717 | B8: AQUATICA EDP 100ML HOMBRE | C8: 1 | D8: 25900 | E8: =C8*D8 -> 25900 | F8: Recibo #21395
A9: 45717 | B9: MAS EDP 100ML UNISEX | C9: 1 | D9: 29900 | E9: =C9*D9 -> 29900 | F9: Recibo #21395
A10: 45717 | B10: VULCAN FEU EDP 100ML UNISEX | C10: 1 | D10: 32900 | E10: =C10*D10 -> 32900 | F10: Recibo #21395
A11: 45717 | B11: ASAD ELIXIR EDP 100ML HOMBRE | C11: 1 | D11: 23900 | E11: =C11*D11 -> 23900 | F11: Recibo #21395
A12: 45717 | B12: HAYAATI EDP 100ML HOMBRE | C12: 1 | D12: 11900 | E12: =C12*D12 -> 11900 | F12: Recibo #21395
A13: 45717 | B13: MANDARIN SKY EDP 100ML HOMBRE | C13: 1 | D13: 25900 | E13: =C13*D13 -> 25900 | F13: Recibo #21395
A14: 45717 | B14: LIQUID BRUN EDP 100ML UNISEX | C14: 1 | D14: 24900 | E14: =C14*D14 -> 24900 | F14: Recibo #21395
A15: 45717 | B15: HAWAS ICE EDP 100ML HOMBRE | C15: 1 | D15: 26900 | E15: =C15*D15 -> 26900 | F15: Recibo #21395
... A24: 45726 | B24: MUESTRA 5ML UNISEX | C24: 1 | D24: 22000 | E24: =C24*D24 -> 22000 | F24: Recibo #21402
E25: =SUM(E4:E15) -> 253800
E26: =SUM(E16:E23) -> 27100
E27: =SUM(E24:E24) -> 22000
A29: TOTAL INVERTIDO: | E29: =SUM(E4:E24) -> 302900
A30: TOTAL UNIDADES: | E30: =SUM(C4:C24) -> 21
A31: TOTAL COMPRAS (recibos): | E31: 3

Sheet Ventas
A1: REGISTRO DE VENTAS - PERFUMES
A2: Escribi TRUE para marcar como vendida (☑) o FALSE para desmarcar (☐) → los datos fluyen solos al dashboard de Ganancias
A3: ☑ Vendido | B3: Fecha | C3: Producto | D3: Cant. Vendida | E3: Precio Venta ($) | F3: Ingreso Total ($) | G3: Costo Total ($) | H3: Ganancia Bruta ($) | I3: Notas
A4: FALSE | C4: QAED AL FURSAN EDP 90ML HOMBRE | D4: 1 | E4: =IF(C4="","",IFERROR(_xlfn.XLOOKUP(C4,Precios!$A$4:$A$24,Precios!$D$4:$D$24,"⚠ Sin precio"),0)) -> 17000 | F4: =IF(A4=TRUE,D4*E4,0) -> 0 | G4: =IF(C4="","",IF(A4=TRUE,D4*IFERROR(_xlfn.XLOOKUP(C4,Precios!$A$4:$A$24,Precios!$B$4:$B$24,0),0),0)) -> 0 | H4: =IF(A4=TRUE,F4-G4,"")
A5: FALSE | C5: ECLAIR EDP 35ML MUJER | D5: 1 | E5: =IF(C5="","",IFERROR(_xlfn.XLOOKUP(C5,Precios!$A$4:$A$24,Precios!$D$4:$D$24,"⚠ Sin precio"),0)) -> 9750 | F5: =IF(A5=TRUE,D5*E5,0) -> 0 | G5: =IF(C5="","",IF(A5=TRUE,D5*IFERROR(_xlfn.XLOOKUP(C5,Precios!$A$4:$A$24,Precios!$B$4:$B$24,0),0),0)) -> 0 | H5: =IF(A5=TRUE,F5-G5,"")
A6: FALSE | C6: RAVE NOW EDP 100ML UNISEX | D6: 1 | E6: =IF(C6="","",IFERROR(_xlfn.XLOOKUP(C6,Precios!$A$4:$A$24,Precios!$D$4:$D$24,"⚠ Sin precio"),0)) -> ⚠ Completar costo y margen | F6: =IF(A6=TRUE,D6*E6,0) -> 0 | G6: =IF(C6="","",IF(A6=TRUE,D6*IFERROR(_xlfn.XLOOKUP(C6,Precios!$A$4:$A$24,Precios!$B$4:$B$24,0),0),0)) -> 0 | H6: =IF(A6=TRUE,F6-G6,"")
A7: FALSE | C7: HAWAS FOR HIM EDP 100ML HOMBRE | D7: 1 | E7: =IF(C7="","",IFERROR(_xlfn.XLOOKUP(C7,Precios!$A$4:$A$24,Precios!$D$4:$D$24,"⚠ Sin precio"),0)) -> ⚠ Completar costo y margen | F7: =IF(A7=TRUE,D7*E7,0) -> 0 | G7: =IF(C7="","",IF(A7=TRUE,D7*IFERROR(_xlfn.XLOOKUP(C7,Precios!$A$4:$A$24,Precios!$B$4:$B$24,0),0),0)) -> 0 | H7: =IF(A7=TRUE,F7-G7,"")
A8: FALSE | C8: AQUATICA EDP 100ML HOMBRE | D8: 1 | E8: =IF(C8="","",IFERROR(_xlfn.XLOOKUP(C8,Precios!$A$4:$A$24,Precios!$D$4:$D$24,"⚠ Sin precio"),0)) -> ⚠ Completar costo y margen | F8: =IF(A8=TRUE,D8*E8,0) -> 0 | G8: =IF(C8="","",IF(A8=TRUE,D8*IFERROR(_xlfn.XLOOKUP(C8,Precios!$A$4:$A$24,Precios!$B$4:$B$24,0),0),0)) -> 0 | H8: =IF(A8=TRUE,F8-G8,"")
A9: FALSE | C9: MAS EDP 100ML UNISEX | D9: 1 | E9: =IF(C9="","",IFERROR(_xlfn.XLOOKUP(C9,Precios!$A$4:$A$24,Precios!$D$4:$D$24,"⚠ Sin precio"),0)) -> ⚠ Completar costo y margen | F9: =IF(A9=TRUE,D9*E9,0) -> 0 | G9: =IF(C9="","",IF(A9=TRUE,D9*IFERROR(_xlfn.XLOOKUP(C9,Precios!$A$4:$A$24,Precios!$B$4:$B$24,0),0),0)) -> 0 | H9: =IF(A9=TRUE,F9-G9,"")
A10: FALSE | C10: VULCAN FEU EDP 100ML UNISEX | D10: 1 | E10: =IF(C10="","",IFERROR(_xlfn.XLOOKUP(C10,Precios!$A$4:$A$24,Precios!$D$4:$D$24,"⚠ Sin precio"),0)) -> ⚠ Completar costo y margen | F10: =IF(A10=TRUE,D10*E10,0) -> 0 | G10: =IF(C10="","",IF(A10=TRUE,D10*IFERROR(_xlfn.XLOOKUP(C10,Precios!$A$4:$A$24,Precios!$B$4:$B$24,0),0),0)) -> 0 | H10: =IF(A10=TRUE,F10-G10,"")
A11: FALSE | C11: ASAD ELIXIR EDP 100ML HOMBRE | D11: 1 | E11: =IF(C11="","",IFERROR(_xlfn.XLOOKUP(C11,Precios!$A$4:$A$24,Precios!$D$4:$D$24,"⚠ Sin precio"),0)) -> ⚠ Completar costo y margen | F11: =IF(A11=TRUE,D11*E11,0) -> 0 | G11: =IF(C11="","",IF(A11=TRUE,D11*IFERROR(_xlfn.XLOOKUP(C11,Precios!$A$4:$A$24,Precios!$B$4:$B$24,0),0),0)) -> 0 | H11: =IF(A11=TRUE,F11-G11,"")
A12: FALSE | C12: HAYAATI EDP 100ML HOMBRE | D12: 1 | E12: =IF(C12="","",IFERROR(_xlfn.XLOOKUP(C12,Precios!$A$4:$A$24,Precios!$D$4:$D$24,"⚠ Sin precio"),0)) -> ⚠ Completar costo y margen | F12: =IF(A12=TRUE,D12*E12,0) -> 0 | G12: =IF(C12="","",IF(A12=TRUE,D12*IFERROR(_xlfn.XLOOKUP(C12,Precios!$A$4:$A$24,Precios!$B$4:$B$24,0),0),0)) -> 0 | H12: =IF(A12=TRUE,F12-G12,"")
A13: FALSE | C13: MANDARIN SKY EDP 100ML HOMBRE | D13: 1 | E13: =IF(C13="","",IFERROR(_xlfn.XLOOKUP(C13,Precios!$A$4:$A$24,Precios!$D$4:$D$24,"⚠ Sin precio"),0)) -> ⚠ Completar costo y margen | F13: =IF(A13=TRUE,D13*E13,0) -> 0 | G13: =IF(C13="","",IF(A13=TRUE,D13*IFERROR(_xlfn.XLOOKUP(C13,Precios!$A$4:$A$24,Precios!$B$4:$B$24,0),0),0)) -> 0 | H13: =IF(A13=TRUE,F13-G13,"")
A14: FALSE | C14: LIQUID BRUN EDP 100ML UNISEX | D14: 1 | E14: =IF(C14="","",IFERROR(_xlfn.XLOOKUP(C14,Precios!$A$4:$A$24,Precios!$D$4:$D$24,"⚠ Sin precio"),0)) -> ⚠ Completar costo y margen | F14: =IF(A14=TRUE,D14*E14,0) -> 0 | G14: =IF(C14="","",IF(A14=TRUE,D14*IFERROR(_xlfn.XLOOKUP(C14,Precios!$A$4:$A$24,Precios!$B$4:$B$24,0),0),0)) -> 0 | H14: =IF(A14=TRUE,F14-G14,"")
A15: FALSE | C15: HAWAS ICE EDP 100ML HOMBRE | D15: 1 | E15: =IF(C15="","",IFERROR(_xlfn.XLOOKUP(C15,Precios!$A$4:$A$24,Precios!$D$4:$D$24,"⚠ Sin precio"),0)) -> ⚠ Completar costo y margen | F15: =IF(A15=TRUE,D15*E15,0) -> 0 | G15: =IF(C15="","",IF(A15=TRUE,D15*IFERROR(_xlfn.XLOOKUP(C15,Precios!$A$4:$A$24,Precios!$B$4:$B$24,0),0),0)) -> 0 | H15: =IF(A15=TRUE,F15-G15,"")
... A24: FALSE | C24: MUESTRA 5ML UNISEX | D24: 1 | E24: =IF(C24="","",IFERROR(_xlfn.XLOOKUP(C24,Precios!$A$4:$A$24,Precios!$D$4:$D$24,"⚠ Sin precio"),0)) -> ⚠ Completar costo y margen | F24: =IF(A24=TRUE,D24*E24,0) -> 0 | G24: =IF(C24="","",IF(A24=TRUE,D24*IFERROR(_xlfn.XLOOKUP(C24,Precios!$A$4:$A$24,Precios!$B$4:$B$24,0),0),0)) -> 0 | H24: =IF(A24=TRUE,F24-G24,"")
A26: TOTALES (ventas confirmadas): | F26: =SUM(F4:F24) -> 0 | G26: =SUM(G4:G24) -> 0 | H26: =SUM(H4:H24) -> 0

Sheet Ganancias
A1: DASHBOARD DE GANANCIAS - PERFUMES
A2: Los datos se actualizan automaticamente a medida que confirmas ventas en la hoja Ventas
A3: RESUMEN ECONOMICO | D3: INDICADORES CLAVE
A4: Total Invertido (Compras) | B4: =Gastos!E29 -> 302900 | D4: Unidades Vendidas (confirmadas) | E4: =COUNTIF(Ventas!A4:A24,TRUE) -> 0
A5: Total Ingresos (Ventas) | B5: =Ventas!F26 -> 0 | D5: Ticket Promedio por Venta | E5: =IFERROR(B5/D4,0) -> 0
A6: Ganancia Bruta | B6: =B5-B4 -> -302900 | D6: Margen Neto % | E6: =IFERROR((B8/B5)*100,0) -> 0
A7: Costo de Ventas (solo lo vendido) | B7: =Ventas!G26 -> 0 | D7: Ganancia Prom. por Unidad | E7: =IFERROR(B8/D4,0) -> 0
A8: Ganancia Neta (Ingresos - Costo Vendido) | B8: =B5-B7 -> 0 | D8: ROI sobre inversion | E8: =IFERROR(B8/B4*100,0) -> 0
A9: ESTADO DEL STOCK | G9: DETALLE POR PRODUCTO
A10: Producto | B10: Comprado | C10: Vendido | D10: Stock Rest. | E10: Estado | G10: Producto | H10: Vendidas | I10: Ingresos ($) | J10: Costo Vend. ($) | K10: Ganancia ($) | L10: Margen %
A11: QAED AL FURSAN EDP 90ML HOMBRE | B11: =IFERROR(SUMIF(Gastos!$B$4:$B$24,"QAED AL FURSAN EDP 90ML HOMBRE",Gastos!$C$4:$C$24),0) -> 1 | C11: =IFERROR(SUMIFS(Ventas!$D$4:$D$24,Ventas!$C$4:$C$24,"QAED AL FURSAN EDP 90ML HOMBRE",Ventas!$A$4:$A$24,TRUE),0) -> 0 | D11: =B11-C11 -> 1 | E11: =IF(D11<=0,"🔴 Sin stock",IF(D11<=2,"🟡 Stock bajo","🟢 OK")) -> 🟡 Stock bajo | G11: QAED AL FURSAN EDP 90ML HOMBRE | H11: =C11 -> 0 | I11: =IFERROR(SUMIFS(Ventas!$F$4:$F$24,Ventas!$C$4:$C$24,"QAED AL FURSAN EDP 90ML HOMBRE",Ventas!$A$4:$A$24,TRUE),0) -> 0 | J11: =IFERROR(SUMIFS(Ventas!$G$4:$G$24,Ventas!$C$4:$C$24,"QAED AL FURSAN EDP 90ML HOMBRE",Ventas!$A$4:$A$24,TRUE),0) -> 0 | K11: =I11-J11 -> 0 | L11: =IFERROR(K11/I11*100,0) -> 0
A12: ECLAIR EDP 35ML MUJER | B12: =IFERROR(SUMIF(Gastos!$B$4:$B$24,"ECLAIR EDP 35ML MUJER",Gastos!$C$4:$C$24),0) -> 1 | C12: =IFERROR(SUMIFS(Ventas!$D$4:$D$24,Ventas!$C$4:$C$24,"ECLAIR EDP 35ML MUJER",Ventas!$A$4:$A$24,TRUE),0) -> 0 | D12: =B12-C12 -> 1 | E12: =IF(D12<=0,"🔴 Sin stock",IF(D12<=2,"🟡 Stock bajo","🟢 OK")) -> 🟡 Stock bajo | G12: ECLAIR EDP 35ML MUJER | H12: =C12 -> 0 | I12: =IFERROR(SUMIFS(Ventas!$F$4:$F$24,Ventas!$C$4:$C$24,"ECLAIR EDP 35ML MUJER",Ventas!$A$4:$A$24,TRUE),0) -> 0 | J12: =IFERROR(SUMIFS(Ventas!$G$4:$G$24,Ventas!$C$4:$C$24,"ECLAIR EDP 35ML MUJER",Ventas!$A$4:$A$24,TRUE),0) -> 0 | K12: =I12-J12 -> 0 | L12: =IFERROR(K12/I12*100,0) -> 0
A13: RAVE NOW EDP 100ML UNISEX | B13: =IFERROR(SUMIF(Gastos!$B$4:$B$24,"RAVE NOW EDP 100ML UNISEX",Gastos!$C$4:$C$24),0) -> 1 | C13: =IFERROR(SUMIFS(Ventas!$D$4:$D$24,Ventas!$C$4:$C$24,"RAVE NOW EDP 100ML UNISEX",Ventas!$A$4:$A$24,TRUE),0) -> 0 | D13: =B13-C13 -> 1 | E13: =IF(D13<=0,"🔴 Sin stock",IF(D13<=2,"🟡 Stock bajo","🟢 OK")) -> 🟡 Stock bajo | G13: RAVE NOW EDP 100ML UNISEX | H13: =C13 -> 0 | I13: =IFERROR(SUMIFS(Ventas!$F$4:$F$24,Ventas!$C$4:$C$24,"RAVE NOW EDP 100ML UNISEX",Ventas!$A$4:$A$24,TRUE),0) -> 0 | J13: =IFERROR(SUMIFS(Ventas!$G$4:$G$24,Ventas!$C$4:$C$24,"RAVE NOW EDP 100ML UNISEX",Ventas!$A$4:$A$24,TRUE),0) -> 0 | K13: =I13-J13 -> 0 | L13: =IFERROR(K13/I13*100,0) -> 0
A14: HAWAS FOR HIM EDP 100ML HOMBRE | B14: =IFERROR(SUMIF(Gastos!$B$4:$B$24,"HAWAS FOR HIM EDP 100ML HOMBRE",Gastos!$C$4:$C$24),0) -> 1 | C14: =IFERROR(SUMIFS(Ventas!$D$4:$D$24,Ventas!$C$4:$C$24,"HAWAS FOR HIM EDP 100ML HOMBRE",Ventas!$A$4:$A$24,TRUE),0) -> 0 | D14: =B14-C14 -> 1 | E14: =IF(D14<=0,"🔴 Sin stock",IF(D14<=2,"🟡 Stock bajo","🟢 OK")) -> 🟡 Stock bajo | G14: HAWAS FOR HIM EDP 100ML HOMBRE | H14: =C14 -> 0 | I14: =IFERROR(SUMIFS(Ventas!$F$4:$F$24,Ventas!$C$4:$C$24,"HAWAS FOR HIM EDP 100ML HOMBRE",Ventas!$A$4:$A$24,TRUE),0) -> 0 | J14: =IFERROR(SUMIFS(Ventas!$G$4:$G$24,Ventas!$C$4:$C$24,"HAWAS FOR HIM EDP 100ML HOMBRE",Ventas!$A$4:$A$24,TRUE),0) -> 0 | K14: =I14-J14 -> 0 | L14: =IFERROR(K14/I14*100,0) -> 0
A15: AQUATICA EDP 100ML HOMBRE | B15: =IFERROR(SUMIF(Gastos!$B$4:$B$24,"AQUATICA EDP 100ML HOMBRE",Gastos!$C$4:$C$24),0) -> 1 | C15: =IFERROR(SUMIFS(Ventas!$D$4:$D$24,Ventas!$C$4:$C$24,"AQUATICA EDP 100ML HOMBRE",Ventas!$A$4:$A$24,TRUE),0) -> 0 | D15: =B15-C15 -> 1 | E15: =IF(D15<=0,"🔴 Sin stock",IF(D15<=2,"🟡 Stock bajo","🟢 OK")) -> 🟡 Stock bajo | G15: AQUATICA EDP 100ML HOMBRE | H15: =C15 -> 0 | I15: =IFERROR(SUMIFS(Ventas!$F$4:$F$24,Ventas!$C$4:$C$24,"AQUATICA EDP 100ML HOMBRE",Ventas!$A$4:$A$24,TRUE),0) -> 0 | J15: =IFERROR(SUMIFS(Ventas!$G$4:$G$24,Ventas!$C$4:$C$24,"AQUATICA EDP 100ML HOMBRE",Ventas!$A$4:$A$24,TRUE),0) -> 0 | K15: =I15-J15 -> 0 | L15: =IFERROR(K15/I15*100,0) -> 0
A16: MAS EDP 100ML UNISEX | B16: =IFERROR(SUMIF(Gastos!$B$4:$B$24,"MAS EDP 100ML UNISEX",Gastos!$C$4:$C$24),0) -> 1 | C16: =IFERROR(SUMIFS(Ventas!$D$4:$D$24,Ventas!$C$4:$C$24,"MAS EDP 100ML UNISEX",Ventas!$A$4:$A$24,TRUE),0) -> 0 | D16: =B16-C16 -> 1 | E16: =IF(D16<=0,"🔴 Sin stock",IF(D16<=2,"🟡 Stock bajo","🟢 OK")) -> 🟡 Stock bajo | G16: MAS EDP 100ML UNISEX | H16: =C16 -> 0 | I16: =IFERROR(SUMIFS(Ventas!$F$4:$F$24,Ventas!$C$4:$C$24,"MAS EDP 100ML UNISEX",Ventas!$A$4:$A$24,TRUE),0) -> 0 | J16: =IFERROR(SUMIFS(Ventas!$G$4:$G$24,Ventas!$C$4:$C$24,"MAS EDP 100ML UNISEX",Ventas!$A$4:$A$24,TRUE),0) -> 0 | K16: =I16-J16 -> 0 | L16: =IFERROR(K16/I16*100,0) -> 0
A17: VULCAN FEU EDP 100ML UNISEX | B17: =IFERROR(SUMIF(Gastos!$B$4:$B$24,"VULCAN FEU EDP 100ML UNISEX",Gastos!$C$4:$C$24),0) -> 1 | C17: =IFERROR(SUMIFS(Ventas!$D$4:$D$24,Ventas!$C$4:$C$24,"VULCAN FEU EDP 100ML UNISEX",Ventas!$A$4:$A$24,TRUE),0) -> 0 | D17: =B17-C17 -> 1 | E17: =IF(D17<=0,"🔴 Sin stock",IF(D17<=2,"🟡 Stock bajo","🟢 OK")) -> 🟡 Stock bajo | G17: VULCAN FEU EDP 100ML UNISEX | H17: =C17 -> 0 | I17: =IFERROR(SUMIFS(Ventas!$F$4:$F$24,Ventas!$C$4:$C$24,"VULCAN FEU EDP 100ML UNISEX",Ventas!$A$4:$A$24,TRUE),0) -> 0 | J17: =IFERROR(SUMIFS(Ventas!$G$4:$G$24,Ventas!$C$4:$C$24,"VULCAN FEU EDP 100ML UNISEX",Ventas!$A$4:$A$24,TRUE),0) -> 0 | K17: =I17-J17 -> 0 | L17: =IFERROR(K17/I17*100,0) -> 0
A18: ASAD ELIXIR EDP 100ML HOMBRE | B18: =IFERROR(SUMIF(Gastos!$B$4:$B$24,"ASAD ELIXIR EDP 100ML HOMBRE",Gastos!$C$4:$C$24),0) -> 1 | C18: =IFERROR(SUMIFS(Ventas!$D$4:$D$24,Ventas!$C$4:$C$24,"ASAD ELIXIR EDP 100ML HOMBRE",Ventas!$A$4:$A$24,TRUE),0) -> 0 | D18: =B18-C18 -> 1 | E18: =IF(D18<=0,"🔴 Sin stock",IF(D18<=2,"🟡 Stock bajo","🟢 OK")) -> 🟡 Stock bajo | G18: ASAD ELIXIR EDP 100ML HOMBRE | H18: =C18 -> 0 | I18: =IFERROR(SUMIFS(Ventas!$F$4:$F$24,Ventas!$C$4:$C$24,"ASAD ELIXIR EDP 100ML HOMBRE",Ventas!$A$4:$A$24,TRUE),0) -> 0 | J18: =IFERROR(SUMIFS(Ventas!$G$4:$G$24,Ventas!$C$4:$C$24,"ASAD ELIXIR EDP 100ML HOMBRE",Ventas!$A$4:$A$24,TRUE),0) -> 0 | K18: =I18-J18 -> 0 | L18: =IFERROR(K18/I18*100,0) -> 0
A19: HAYAATI EDP 100ML HOMBRE | B19: =IFERROR(SUMIF(Gastos!$B$4:$B$24,"HAYAATI EDP 100ML HOMBRE",Gastos!$C$4:$C$24),0) -> 1 | C19: =IFERROR(SUMIFS(Ventas!$D$4:$D$24,Ventas!$C$4:$C$24,"HAYAATI EDP 100ML HOMBRE",Ventas!$A$4:$A$24,TRUE),0) -> 0 | D19: =B19-C19 -> 1 | E19: =IF(D19<=0,"🔴 Sin stock",IF(D19<=2,"🟡 Stock bajo","🟢 OK")) -> 🟡 Stock bajo | G19: HAYAATI EDP 100ML HOMBRE | H19: =C19 -> 0 | I19: =IFERROR(SUMIFS(Ventas!$F$4:$F$24,Ventas!$C$4:$C$24,"HAYAATI EDP 100ML HOMBRE",Ventas!$A$4:$A$24,TRUE),0) -> 0 | J19: =IFERROR(SUMIFS(Ventas!$G$4:$G$24,Ventas!$C$4:$C$24,"HAYAATI EDP 100ML HOMBRE",Ventas!$A$4:$A$24,TRUE),0) -> 0 | K19: =I19-J19 -> 0 | L19: =IFERROR(K19/I19*100,0) -> 0
A20: MANDARIN SKY EDP 100ML HOMBRE | B20: =IFERROR(SUMIF(Gastos!$B$4:$B$24,"MANDARIN SKY EDP 100ML HOMBRE",Gastos!$C$4:$C$24),0) -> 1 | C20: =IFERROR(SUMIFS(Ventas!$D$4:$D$24,Ventas!$C$4:$C$24,"MANDARIN SKY EDP 100ML HOMBRE",Ventas!$A$4:$A$24,TRUE),0) -> 0 | D20: =B20-C20 -> 1 | E20: =IF(D20<=0,"🔴 Sin stock",IF(D20<=2,"🟡 Stock bajo","🟢 OK")) -> 🟡 Stock bajo | G20: MANDARIN SKY EDP 100ML HOMBRE | H20: =C20 -> 0 | I20: =IFERROR(SUMIFS(Ventas!$F$4:$F$24,Ventas!$C$4:$C$24,"MANDARIN SKY EDP 100ML HOMBRE",Ventas!$A$4:$A$24,TRUE),0) -> 0 | J20: =IFERROR(SUMIFS(Ventas!$G$4:$G$24,Ventas!$C$4:$C$24,"MANDARIN SKY EDP 100ML HOMBRE",Ventas!$A$4:$A$24,TRUE),0) -> 0 | K20: =I20-J20 -> 0 | L20: =IFERROR(K20/I20*100,0) -> 0
A21: LIQUID BRUN EDP 100ML UNISEX | B21: =IFERROR(SUMIF(Gastos!$B$4:$B$24,"LIQUID BRUN EDP 100ML UNISEX",Gastos!$C$4:$C$24),0) -> 1 | C21: =IFERROR(SUMIFS(Ventas!$D$4:$D$24,Ventas!$C$4:$C$24,"LIQUID BRUN EDP 100ML UNISEX",Ventas!$A$4:$A$24,TRUE),0) -> 0 | D21: =B21-C21 -> 1 | E21: =IF(D21<=0,"🔴 Sin stock",IF(D21<=2,"🟡 Stock bajo","🟢 OK")) -> 🟡 Stock bajo | G21: LIQUID BRUN EDP 100ML UNISEX | H21: =C21 -> 0 | I21: =IFERROR(SUMIFS(Ventas!$F$4:$F$24,Ventas!$C$4:$C$24,"LIQUID BRUN EDP 100ML UNISEX",Ventas!$A$4:$A$24,TRUE),0) -> 0 | J21: =IFERROR(SUMIFS(Ventas!$G$4:$G$24,Ventas!$C$4:$C$24,"LIQUID BRUN EDP 100ML UNISEX",Ventas!$A$4:$A$24,TRUE),0) -> 0 | K21: =I21-J21 -> 0 | L21: =IFERROR(K21/I21*100,0) -> 0
A22: HAWAS ICE EDP 100ML HOMBRE | B22: =IFERROR(SUMIF(Gastos!$B$4:$B$24,"HAWAS ICE EDP 100ML HOMBRE",Gastos!$C$4:$C$24),0) -> 1 | C22: =IFERROR(SUMIFS(Ventas!$D$4:$D$24,Ventas!$C$4:$C$24,"HAWAS ICE EDP 100ML HOMBRE",Ventas!$A$4:$A$24,TRUE),0) -> 0 | D22: =B22-C22 -> 1 | E22: =IF(D22<=0,"🔴 Sin stock",IF(D22<=2,"🟡 Stock bajo","🟢 OK")) -> 🟡 Stock bajo | G22: HAWAS ICE EDP 100ML HOMBRE | H22: =C22 -> 0 | I22: =IFERROR(SUMIFS(Ventas!$F$4:$F$24,Ventas!$C$4:$C$24,"HAWAS ICE EDP 100ML HOMBRE",Ventas!$A$4:$A$24,TRUE),0) -> 0 | J22: =IFERROR(SUMIFS(Ventas!$G$4:$G$24,Ventas!$C$4:$C$24,"HAWAS ICE EDP 100ML HOMBRE",Ventas!$A$4:$A$24,TRUE),0) -> 0 | K22: =I22-J22 -> 0 | L22: =IFERROR(K22/I22*100,0) -> 0
A23: ASAD EDP 30ML HOMBRE | B23: =IFERROR(SUMIF(Gastos!$B$4:$B$24,"ASAD EDP 30ML HOMBRE",Gastos!$C$4:$C$24),0) -> 1 | C23: =IFERROR(SUMIFS(Ventas!$D$4:$D$24,Ventas!$C$4:$C$24,"ASAD EDP 30ML HOMBRE",Ventas!$A$4:$A$24,TRUE),0) -> 0 | D23: =B23-C23 -> 1 | E23: =IF(D23<=0,"🔴 Sin stock",IF(D23<=2,"🟡 Stock bajo","🟢 OK")) -> 🟡 Stock bajo | G23: ASAD EDP 30ML HOMBRE | H23: =C23 -> 0 | I23: =IFERROR(SUMIFS(Ventas!$F$4:$F$24,Ventas!$C$4:$C$24,"ASAD EDP 30ML HOMBRE",Ventas!$A$4:$A$24,TRUE),0) -> 0 | J23: =IFERROR(SUMIFS(Ventas!$G$4:$G$24,Ventas!$C$4:$C$24,"ASAD EDP 30ML HOMBRE",Ventas!$A$4:$A$24,TRUE),0) -> 0 | K23: =I23-J23 -> 0 | L23: =IFERROR(K23/I23*100,0) -> 0
A24: OUD FOR GLORY WHITE EDP 30ML UNISEX | B24: =IFERROR(SUMIF(Gastos!$B$4:$B$24,"OUD FOR GLORY WHITE EDP 30ML UNISEX",Gastos!$C$4:$C$24),0) -> 1 | C24: =IFERROR(SUMIFS(Ventas!$D$4:$D$24,Ventas!$C$4:$C$24,"OUD FOR GLORY WHITE EDP 30ML UNISEX",Ventas!$A$4:$A$24,TRUE),0) -> 0 | D24: =B24-C24 -> 1 | E24: =IF(D24<=0,"🔴 Sin stock",IF(D24<=2,"🟡 Stock bajo","🟢 OK")) -> 🟡 Stock bajo | G24: OUD FOR GLORY WHITE EDP 30ML UNISEX | H24: =C24 -> 0 | I24: =IFERROR(SUMIFS(Ventas!$F$4:$F$24,Ventas!$C$4:$C$24,"OUD FOR GLORY WHITE EDP 30ML UNISEX",Ventas!$A$4:$A$24,TRUE),0) -> 0 | J24: =IFERROR(SUMIFS(Ventas!$G$4:$G$24,Ventas!$C$4:$C$24,"OUD FOR GLORY WHITE EDP 30ML UNISEX",Ventas!$A$4:$A$24,TRUE),0) -> 0 | K24: =I24-J24 -> 0 | L24: =IFERROR(K24/I24*100,0) -> 0
A25: SCANDAL EDP 25ML HOMBRE | B25: =IFERROR(SUMIF(Gastos!$B$4:$B$24,"SCANDAL EDP 25ML HOMBRE",Gastos!$C$4:$C$24),0) -> 1 | C25: =IFERROR(SUMIFS(Ventas!$D$4:$D$24,Ventas!$C$4:$C$24,"SCANDAL EDP 25ML HOMBRE",Ventas!$A$4:$A$24,TRUE),0) -> 0 | D25: =B25-C25 -> 1 | E25: =IF(D25<=0,"🔴 Sin stock",IF(D25<=2,"🟡 Stock bajo","🟢 OK")) -> 🟡 Stock bajo | G25: SCANDAL EDP 25ML HOMBRE | H25: =C25 -> 0 | I25: =IFERROR(SUMIFS(Ventas!$F$4:$F$24,Ventas!$C$4:$C$24,"SCANDAL EDP 25ML HOMBRE",Ventas!$A$4:$A$24,TRUE),0) -> 0 | J25: =IFERROR(SUMIFS(Ventas!$G$4:$G$24,Ventas!$C$4:$C$24,"SCANDAL EDP 25ML HOMBRE",Ventas!$A$4:$A$24,TRUE),0) -> 0 | K25: =I25-J25 -> 0 | L25: =IFERROR(K25/I25*100,0) -> 0
A26: SCANDAL WOMEN EDP 30ML MUJER | B26: =IFERROR(SUMIF(Gastos!$B$4:$B$24,"SCANDAL WOMEN EDP 30ML MUJER",Gastos!$C$4:$C$24),0) -> 1 | C26: =IFERROR(SUMIFS(Ventas!$D$4:$D$24,Ventas!$C$4:$C$24,"SCANDAL WOMEN EDP 30ML MUJER",Ventas!$A$4:$A$24,TRUE),0) -> 0 | D26: =B26-C26 -> 1 | E26: =IF(D26<=0,"🔴 Sin stock",IF(D26<=2,"🟡 Stock bajo","🟢 OK")) -> 🟡 Stock bajo | G26: SCANDAL WOMEN EDP 30ML MUJER | H26: =C26 -> 0 | I26: =IFERROR(SUMIFS(Ventas!$F$4:$F$24,Ventas!$C$4:$C$24,"SCANDAL WOMEN EDP 30ML MUJER",Ventas!$A$4:$A$24,TRUE),0) -> 0 | J26: =IFERROR(SUMIFS(Ventas!$G$4:$G$24,Ventas!$C$4:$C$24,"SCANDAL WOMEN EDP 30ML MUJER",Ventas!$A$4:$A$24,TRUE),0) -> 0 | K26: =I26-J26 -> 0 | L26: =IFERROR(K26/I26*100,0) -> 0
A27: SARA CANDY EDP 30ML MUJER | B27: =IFERROR(SUMIF(Gastos!$B$4:$B$24,"SARA CANDY EDP 30ML MUJER",Gastos!$C$4:$C$24),0) -> 1 | C27: =IFERROR(SUMIFS(Ventas!$D$4:$D$24,Ventas!$C$4:$C$24,"SARA CANDY EDP 30ML MUJER",Ventas!$A$4:$A$24,TRUE),0) -> 0 | D27: =B27-C27 -> 1 | E27: =IF(D27<=0,"🔴 Sin stock",IF(D27<=2,"🟡 Stock bajo","🟢 OK")) -> 🟡 Stock bajo | G27: SARA CANDY EDP 30ML MUJER | H27: =C27 -> 0 | I27: =IFERROR(SUMIFS(Ventas!$F$4:$F$24,Ventas!$C$4:$C$24,"SARA CANDY EDP 30ML MUJER",Ventas!$A$4:$A$24,TRUE),0) -> 0 | J27: =IFERROR(SUMIFS(Ventas!$G$4:$G$24,Ventas!$C$4:$C$24,"SARA CANDY EDP 30ML MUJER",Ventas!$A$4:$A$24,TRUE),0) -> 0 | K27: =I27-J27 -> 0 | L27: =IFERROR(K27/I27*100,0) -> 0
A28: KAMRAH EDP 30ML HOMBRE | B28: =IFERROR(SUMIF(Gastos!$B$4:$B$24,"KAMRAH EDP 30ML HOMBRE",Gastos!$C$4:$C$24),0) -> 1 | C28: =IFERROR(SUMIFS(Ventas!$D$4:$D$24,Ventas!$C$4:$C$24,"KAMRAH EDP 30ML HOMBRE",Ventas!$A$4:$A$24,TRUE),0) -> 0 | D28: =B28-C28 -> 1 | E28: =IF(D28<=0,"🔴 Sin stock",IF(D28<=2,"🟡 Stock bajo","🟢 OK")) -> 🟡 Stock bajo | G28: KAMRAH EDP 30ML HOMBRE | H28: =C28 -> 0 | I28: =IFERROR(SUMIFS(Ventas!$F$4:$F$24,Ventas!$C$4:$C$24,"KAMRAH EDP 30ML HOMBRE",Ventas!$A$4:$A$24,TRUE),0) -> 0 | J28: =IFERROR(SUMIFS(Ventas!$G$4:$G$24,Ventas!$C$4:$C$24,"KAMRAH EDP 30ML HOMBRE",Ventas!$A$4:$A$24,TRUE),0) -> 0 | K28: =I28-J28 -> 0 | L28: =IFERROR(K28/I28*100,0) -> 0
A29: NOW PINK EDP 30ML MUJER | B29: =IFERROR(SUMIF(Gastos!$B$4:$B$24,"NOW PINK EDP 30ML MUJER",Gastos!$C$4:$C$24),0) -> 1 | C29: =IFERROR(SUMIFS(Ventas!$D$4:$D$24,Ventas!$C$4:$C$24,"NOW PINK EDP 30ML MUJER",Ventas!$A$4:$A$24,TRUE),0) -> 0 | D29: =B29-C29 -> 1 | E29: =IF(D29<=0,"🔴 Sin stock",IF(D29<=2,"🟡 Stock bajo","🟢 OK")) -> 🟡 Stock bajo | G29: NOW PINK EDP 30ML MUJER | H29: =C29 -> 0 | I29: =IFERROR(SUMIFS(Ventas!$F$4:$F$24,Ventas!$C$4:$C$24,"NOW PINK EDP 30ML MUJER",Ventas!$A$4:$A$24,TRUE),0) -> 0 | J29: =IFERROR(SUMIFS(Ventas!$G$4:$G$24,Ventas!$C$4:$C$24,"NOW PINK EDP 30ML MUJER",Ventas!$A$4:$A$24,TRUE),0) -> 0 | K29: =I29-J29 -> 0 | L29: =IFERROR(K29/I29*100,0) -> 0
A30: HAYAATI BODY MIST 250ML HOMBRE | B30: =IFERROR(SUMIF(Gastos!$B$4:$B$24,"HAYAATI BODY MIST 250ML HOMBRE",Gastos!$C$4:$C$24),0) -> 1 | C30: =IFERROR(SUMIFS(Ventas!$D$4:$D$24,Ventas!$C$4:$C$24,"HAYAATI BODY MIST 250ML HOMBRE",Ventas!$A$4:$A$24,TRUE),0) -> 0 | D30: =B30-C30 -> 1 | E30: =IF(D30<=0,"🔴 Sin stock",IF(D30<=2,"🟡 Stock bajo","🟢 OK")) -> 🟡 Stock bajo | G30: HAYAATI BODY MIST 250ML HOMBRE | H30: =C30 -> 0 | I30: =IFERROR(SUMIFS(Ventas!$F$4:$F$24,Ventas!$C$4:$C$24,"HAYAATI BODY MIST 250ML HOMBRE",Ventas!$A$4:$A$24,TRUE),0) -> 0 | J30: =IFERROR(SUMIFS(Ventas!$G$4:$G$24,Ventas!$C$4:$C$24,"HAYAATI BODY MIST 250ML HOMBRE",Ventas!$A$4:$A$24,TRUE),0) -> 0 | K30: =I30-J30 -> 0 | L30: =IFERROR(K30/I30*100,0) -> 0
A31: MUESTRA 5ML UNISEX | B31: =IFERROR(SUMIF(Gastos!$B$4:$B$24,"MUESTRA 5ML UNISEX",Gastos!$C$4:$C$24),0) -> 1 | C31: =IFERROR(SUMIFS(Ventas!$D$4:$D$24,Ventas!$C$4:$C$24,"MUESTRA 5ML UNISEX",Ventas!$A$4:$A$24,TRUE),0) -> 0 | D31: =B31-C31 -> 1 | E31: =IF(D31<=0,"🔴 Sin stock",IF(D31<=2,"🟡 Stock bajo","🟢 OK")) -> 🟡 Stock bajo | G31: MUESTRA 5ML UNISEX | H31: =C31 -> 0 | I31: =IFERROR(SUMIFS(Ventas!$F$4:$F$24,Ventas!$C$4:$C$24,"MUESTRA 5ML UNISEX",Ventas!$A$4:$A$24,TRUE),0) -> 0 | J31: =IFERROR(SUMIFS(Ventas!$G$4:$G$24,Ventas!$C$4:$C$24,"MUESTRA 5ML UNISEX",Ventas!$A$4:$A$24,TRUE),0) -> 0 | K31: =I31-J31 -> 0 | L31: =IFERROR(K31/I31*100,0) -> 0
A32: TOTAL | B32: =SUM(B11:B31) -> 21 | C32: =SUM(C11:C31) -> 0 | D32: =SUM(D11:D31) -> 21 | E32: =IF(D32<=0,"🔴 Sin stock",IF(D32<=2,"🟡 Stock bajo","🟢 OK")) -> 🟢 OK | G32: TOTAL | H32: =SUM(H11:H31) -> 0 | I32: =SUM(I11:I31) -> 0 | J32: =SUM(J11:J31) -> 0 | K32: =SUM(K11:K31) -> 0 | L32: =IFERROR(K32/I32*100,0) -> 0
A34: 🟢 OK = stock disponible 🟡 Stock bajo (≤2 unidades) 🔴 Sin stock | Tilda ventas en hoja Ventas → dashboard se actualiza solo

Sheet ChartData
A1: Producto | B1: Costo ($) | D1: Recibo | E1: Total ($)
A2: QAED AL FURSAN 90ML | B2: =Gastos!E4 -> 11900 | D2: Recibo #21395 | E2: =SUMIF(Gastos!F4:F24,"Recibo #21395",Gastos!E4:E24) -> 253800
A3: ECLAIR 35ML | B3: =Gastos!E5 -> 3900 | D3: Recibo #21398 | E3: =SUMIF(Gastos!F4:F24,"Recibo #21398",Gastos!E4:E24) -> 27100
A4: RAVE NOW 100ML | B4: =Gastos!E6 -> 13900 | D4: Recibo #21402 | E4: =SUMIF(Gastos!F4:F24,"Recibo #21402",Gastos!E4:E24) -> 22000
A5: HAWAS FOR HIM 100ML | B5: =Gastos!E7 -> 21900
A6: AQUATICA 100ML | B6: =Gastos!E8 -> 25900
A7: MAS 100ML | B7: =Gastos!E9 -> 29900
A8: VULCAN FEU 100ML | B8: =Gastos!E10 -> 32900
A9: ASAD ELIXIR 100ML | B9: =Gastos!E11 -> 23900
A10: HAYAATI 100ML | B10: =Gastos!E12 -> 11900
A11: MANDARIN SKY 100ML | B11: =Gastos!E13 -> 25900
A12: LIQUID BRUN 100ML | B12: =Gastos!E14 -> 24900
A13: HAWAS ICE 100ML | B13: =Gastos!E15 -> 26900
A14: ASAD 30ML | B14: =Gastos!E16 -> 2900
A15: OUD FOR GLORY 30ML | B15: =Gastos!E17 -> 2900
A16: SCANDAL 25ML | B16: =Gastos!E18 -> 2900
... A22: MUESTRA 5ML | B22: =Gastos!E24 -> 22000
